ssb_pseudonymization/__init__.py
ssb_pseudonymization/exceptions.py
ssb_pseudonymization/pseudo.py
ssb_pseudonymization/pseudo_func.py
ssb_pseudonymization/util.py
ssb_pseudonymization/func/__init__.py
ssb_pseudonymization/func/fpe.py
ssb_pseudonymization/func/lookuptable.py
ssb_pseudonymization-0.0.2.dist-info/LICENSE
ssb_pseudonymization-0.0.2.dist-info/METADATA
ssb_pseudonymization-0.0.2.dist-info/WHEEL
ssb_pseudonymization-0.0.2.dist-info/top_level.txt
ssb_pseudonymization-0.0.2.dist-info/RECORD
