Metadata-Version: 2.1
Name: ssb-pseudonymization
Version: 0.0.2
Summary: Data pseudonymization functions used by SSB
Home-page: https://github.com/statisticsnorway/ssb-pseudonymization-py
Author: Statistics Norway
Author-email: ks@udp.no
License: MIT
Platform: UNKNOWN
Classifier: Development Status :: 2 - Pre-Alpha
Classifier: License :: OSI Approved :: MIT License
Classifier: Programming Language :: Python
Classifier: Programming Language :: Python :: 2
Classifier: Programming Language :: Python :: 2.7
Classifier: Programming Language :: Python :: 3
Classifier: Programming Language :: Python :: 3.5
Classifier: Programming Language :: Python :: 3.6
Classifier: Programming Language :: Python :: 3.7
Requires-Dist: pyffx (>=0.3.0)
